pytorchsummary/__init__.py
pytorchsummary/pytorchsummary.py
pytorchsummary-1.3.0.dist-info/METADATA
pytorchsummary-1.3.0.dist-info/WHEEL
pytorchsummary-1.3.0.dist-info/top_level.txt
pytorchsummary-1.3.0.dist-info/RECORD
