Metadata-Version: 2.1
Name: pytorchsummary
Version: 1.3.0
Summary: Summary of PyTorch Models just like `model.summary() in Keras
Home-page: https://github.com/GSAUC3/pytorch-model-details
Author: Rajarshi Banerjee
Author-email: raju.banerjee.720@gmail.com
License: MIT
Keywords: python,PyTorch,Pytorch model summary,Pytorch parameter summary
Classifier: Programming Language :: Python :: 3.8
Classifier: License :: OSI Approved :: MIT License
